bai_stats/__init__.py
bai_stats/goodness_of_fit.py
bai_stats-0.1.0.dist-info/METADATA
bai_stats-0.1.0.dist-info/WHEEL
bai_stats-0.1.0.dist-info/top_level.txt
bai_stats-0.1.0.dist-info/RECORD
