Metadata-Version: 2.1
Name: bai-stats
Version: 0.1.0
Summary: Package for statistical analysis
Home-page: https://github.com/pypa/sampleproject
Author: Sudhir Aithal
Author-email: aithalsudhir@gmail.com
License: UNKNOWN
Platform: UNKNOWN
Classifier: Programming Language :: Python :: 3
Classifier: License :: OSI Approved :: MIT License
Classifier: Operating System :: OS Independent
